histopca/__init__.py
histopca/histogram_pca.py
histopca/r_compatible.py
histopca-0.1.2.dist-info/licenses/LICENSE
histopca-0.1.2.dist-info/METADATA
histopca-0.1.2.dist-info/WHEEL
histopca-0.1.2.dist-info/top_level.txt
histopca-0.1.2.dist-info/RECORD
