Metadata-Version: 2.4
Name: histopca
Version: 0.1.2
Summary: Principal Component Analysis on Histogram-Binned Distributional Data
Home-page: https://github.com/brahim7/foursight.ai_histopca
Author: Bibi Brahim and Sun Makosso Alix
Author-email: Bibi Brahim and Sun Makosso Alix <brahim_b@foursight.ai>
Maintainer: Bibi Brahim
Maintainer-email: Bibi Brahim <brahim_b@foursight.ai>
License: AGPL-3.0-or-later
Project-URL: Homepage, https://github.com/brahim7/foursight.ai_histopca
Project-URL: Documentation, https://github.com/brahim7/foursight.ai_histopca#readme
Project-URL: Repository, https://github.com/brahim7/foursight.ai_histopca.git
Project-URL: Bug Tracker, https://github.com/brahim7/foursight.ai_histopca/issues
Keywords: pca,histogram,distributional-data,statistics,data-analysis
Classifier: Development Status :: 3 - Alpha
Classifier: Intended Audience :: Science/Research
Classifier: Intended Audience :: Developers
Classifier: License :: OSI Approved :: GNU Affero General Public License v3 or later (AGPLv3+)
Classifier: Operating System :: OS Independent
Classifier: Programming Language :: Python :: 3
Classifier: Programming Language :: Python :: 3.8
Classifier: Programming Language :: Python :: 3.9
Classifier: Programming Language :: Python :: 3.10
Classifier: Programming Language :: Python :: 3.11
Classifier: Programming Language :: Python :: 3.12
Classifier: Topic :: Scientific/Engineering
Classifier: Topic :: Scientific/Engineering :: Mathematics
Classifier: Topic :: Software Development :: Libraries :: Python Modules
Requires-Python: >=3.8
License-File: LICENSE
Requires-Dist: numpy>=1.20.0
Requires-Dist: pandas>=1.3.0
Requires-Dist: scipy>=1.7.0
Requires-Dist: matplotlib>=3.4.0
Requires-Dist: seaborn>=0.11.0
Dynamic: author
Dynamic: home-page
Dynamic: license-file
Dynamic: maintainer
Dynamic: requires-python
